basana/__init__.py
basana/backtesting/__init__.py
basana/backtesting/account_balances.py
basana/backtesting/charts.py
basana/backtesting/config.py
basana/backtesting/errors.py
basana/backtesting/exchange.py
basana/backtesting/fees.py
basana/backtesting/helpers.py
basana/backtesting/lending/__init__.py
basana/backtesting/lending/base.py
basana/backtesting/lending/margin.py
basana/backtesting/liquidity.py
basana/backtesting/loan_mgr.py
basana/backtesting/order_mgr.py
basana/backtesting/orders.py
basana/backtesting/prices.py
basana/backtesting/requests.py
basana/backtesting/value_map.py
basana/core/__init__.py
basana/core/bar.py
basana/core/config.py
basana/core/dispatcher.py
basana/core/dt.py
basana/core/enums.py
basana/core/errors.py
basana/core/event.py
basana/core/event_sources/__init__.py
basana/core/event_sources/csv.py
basana/core/event_sources/trading_signal.py
basana/core/helpers.py
basana/core/logs.py
basana/core/pair.py
basana/core/token_bucket.py
basana/core/websockets.py
basana/external/__init__.py
basana/external/binance/__init__.py
basana/external/binance/client/__init__.py
basana/external/binance/client/base.py
basana/external/binance/client/margin.py
basana/external/binance/client/spot.py
basana/external/binance/common.py
basana/external/binance/config.py
basana/external/binance/cross_margin.py
basana/external/binance/csv/__init__.py
basana/external/binance/csv/bars.py
basana/external/binance/exchange.py
basana/external/binance/helpers.py
basana/external/binance/isolated_margin.py
basana/external/binance/klines.py
basana/external/binance/margin.py
basana/external/binance/margin_requests.py
basana/external/binance/order_book.py
basana/external/binance/order_book_diff.py
basana/external/binance/spot.py
basana/external/binance/spot_requests.py
basana/external/binance/tools/__init__.py
basana/external/binance/tools/download_bars.py
basana/external/binance/trades.py
basana/external/binance/user_data.py
basana/external/binance/websocket_mgr.py
basana-1.10.1.dist-info/METADATA
basana-1.10.1.dist-info/WHEEL
basana-1.10.1.dist-info/licenses/LICENSE
basana-1.10.1.dist-info/RECORD
